circle/__init__.py
circle/code.py
square/__init__.py
square/code.py
triangle/__init__.py
triangle/code.py
my_new_math_package-0.1.dist-info/METADATA
my_new_math_package-0.1.dist-info/WHEEL
my_new_math_package-0.1.dist-info/top_level.txt
my_new_math_package-0.1.dist-info/RECORD
