Metadata-Version: 2.1
Name: my-new-math-package
Version: 0.1
Summary: simple math
License: MIT
